dou_tools/__init__.py
dou_tools/core.py
dou_tools-0.1.5.dist-info/METADATA
dou_tools-0.1.5.dist-info/WHEEL
dou_tools-0.1.5.dist-info/top_level.txt
dou_tools-0.1.5.dist-info/RECORD
