Metadata-Version: 2.4
Name: dou-tools
Version: 0.1.5
Summary: Example DOU tools Python library
Author: Valentyn Druzhynin
License: MIT
Provides-Extra: dev
Requires-Dist: pytest; extra == "dev"
Requires-Dist: twine; extra == "dev"
Requires-Dist: build; extra == "dev"
